easycpp/__init__.py
easycpp/easycpp.py
easycpp/precompile/__init__.py
easycpp/precompile/main.py
easycpp-1.0.1.dist-info/METADATA
easycpp-1.0.1.dist-info/WHEEL
easycpp-1.0.1.dist-info/entry_points.txt
easycpp-1.0.1.dist-info/top_level.txt
easycpp-1.0.1.dist-info/RECORD
