Metadata-Version: 2.4
Name: easycpp
Version: 1.0.1
Summary: Using embedded C++ code in .py
Home-page: https://github.com/chrisju/easycpp
Author: Chris Ju
Author-email: Chris Ju <mchrisju@gmail.com>
License: MIT
Project-URL: Homepage, https://github.com/chrisju/easycpp
Classifier: Programming Language :: Python :: 3
Requires-Python: >=3.7
Dynamic: author
Dynamic: home-page
Dynamic: requires-python
